[{"id": "827a9915", "chain": "base", "token": "DIEM", "t0": "2026-07-02T15:01:59.732605+00:00", "entry_spread": 0.7195, "lo_dex": "aerodrome", "hi_dex": "aerodrome", "min_tvl": 3598534.25, "whale": false, "samples": [[0.0, 0.7195, 0.1068], [1.8, 0.3721, -1.5355], [3.6, 0.3721, -1.5355], [5.3, 0.3721, -1.5355], [18.1, 0.1834, -1.7395], [19.8, 0.1834, -1.7395], [21.4, 0.1834, -1.7395], [23.1, 0.1834, -1.7395], [24.7, 0.1834, -1.7395], [26.4, 0.1834, -1.7304], [28.0, 0.219, -1.6944], [29.7, 0.219, -1.6944]]}, {"id": "8dacdf3c", "chain": "base", "token": "AERO", "t0": "2026-07-02T15:21:46.267299+00:00", "entry_spread": 1.1034, "lo_dex": "aerodrome", "hi_dex": "aerodrome", "min_tvl": 670531.48, "whale": true, "samples": [[0.0, 1.1034, 0.0054], [1.6, 1.0039, 0.3562], [3.3, 0.845, 0.1973], [5.0, 0.746, -0.4854], [6.6, 0.6471, -1.0242], [8.3, 0.8431, -0.8281], [9.9, 0.9412, -0.7301]]}, {"id": "486d6a22", "chain": "base", "token": "VIRTUAL", "t0": "2026-07-02T15:21:46.267299+00:00", "entry_spread": 0.9256, "lo_dex": "aerodrome", "hi_dex": "aerodrome", "min_tvl": 390659.22, "whale": true, "samples": [[0.0, 0.9256, -0.5998], [1.6, 0.8158, -0.5315], [3.3, 0.9971, -0.3502], [5.0, 1.1059, -0.2414], [6.6, 1.1603, -0.187], [8.3, 1.1421, -0.2051], [9.9, 1.1605, -0.1868]]}, {"id": "58bf4054", "chain": "base", "token": "CBBTC", "t0": "2026-07-02T15:21:46.267299+00:00", "entry_spread": 0.8529, "lo_dex": "aerodrome", "hi_dex": "aerodrome", "min_tvl": 527088.74, "whale": true, "samples": [[0.0, 0.8529, -0.4075], [1.6, 0.8529, -0.4075], [3.3, 0.8529, -0.4075], [5.0, 0.8529, -0.4075], [6.6, 1.1324, -0.128], [8.3, 1.2433, -0.0171], [9.9, 1.2433, -0.0171]]}, {"id": "48b6bf05", "chain": "solana", "token": "POPCAT", "t0": "2026-07-02T15:23:24.992982+00:00", "entry_spread": 1.1891, "lo_dex": "raydium", "hi_dex": "raydium", "min_tvl": 570879.75, "whale": false, "samples": [[0.0, 1.1891, -0.0121], [1.7, 0.2288, -0.9767], [3.3, 0.3204, -0.8852], [5.0, 0.2975, -0.9081], [6.6, 0.2053, -0.9985], [8.3, 0.274, -0.9298]]}, {"id": "dd3a4259", "chain": "solana", "token": "MET", "t0": "2026-07-02T15:25:05.564593+00:00", "entry_spread": 166.792, "lo_dex": "meteora", "hi_dex": "meteora", "min_tvl": 368462.6, "whale": true, "samples": [[0.0, 166.792, 165.206], [1.6, 166.792, 165.206], [3.3, 166.792, 165.206], [4.9, 166.792, 165.206], [6.6, 166.792, 165.206]]}, {"id": "e05ceb7e", "chain": "solana", "token": "GIGA", "t0": "2026-07-02T15:28:23.252668+00:00", "entry_spread": 1.6826, "lo_dex": "meteora", "hi_dex": "raydium", "min_tvl": 258742.65, "whale": false, "samples": [[0.0, 1.6826, -0.3638], [1.6, 1.6061, -0.4403], [3.3, 1.5679, -0.4786]]}, {"id": "8e477135", "chain": "solana", "token": "SOL", "t0": "2026-07-02T15:28:23.252668+00:00", "entry_spread": 0.6595, "lo_dex": "raydium", "hi_dex": "raydium", "min_tvl": 960443.71, "whale": true, "samples": [[0.0, 0.6595, -0.2575], [1.6, 0.2731, -0.3668], [3.3, 0.4977, -0.4196]]}, {"id": "370ce846", "chain": "base", "token": "WETH", "t0": "2026-07-02T15:28:23.252668+00:00", "entry_spread": 0.4561, "lo_dex": "uniswap", "hi_dex": "uniswap", "min_tvl": 791418.87, "whale": true, "samples": [[0.0, 0.4561, -0.5508], [1.6, 0.4502, -0.5567], [3.3, 0.4502, -0.5567]]}, {"id": "7feeaaf2", "chain": "solana", "token": "ORE", "t0": "2026-07-02T15:31:40.954395+00:00", "entry_spread": 1.7965, "lo_dex": "orca", "hi_dex": "meteora", "min_tvl": 305063.38, "whale": true, "samples": [[0.0, 1.7965, -0.0152]]}, {"id": "e3b32f79", "chain": "solana", "token": "JITOSOL", "t0": "2026-07-02T15:31:40.954395+00:00", "entry_spread": 0.4933, "lo_dex": "meteora", "hi_dex": "orca", "min_tvl": 2190699.87, "whale": true, "samples": [[0.0, 0.4933, -0.1898]]}]