[{"id": "d4d4ff40", "chain": "base", "token": "CBBTC", "t0": "2026-06-27T20:50:55.135942+00:00", "entry_spread": 1.0305, "lo_dex": "aerodrome", "hi_dex": "aerodrome", "min_tvl": 503413.04, "whale": true, "samples": [[0.0, 1.0305, -0.2656], [1.8, 1.0305, -0.2656], [3.6, 1.0305, -0.2656], [5.4, 1.0305, -0.2656], [7.2, 1.0305, -0.2656], [9.0, 1.0305, -0.2656], [10.8, 1.0305, -0.2656]]}, {"id": "6a936107", "chain": "base", "token": "VIRTUAL", "t0": "2026-06-27T20:50:55.135942+00:00", "entry_spread": 0.8608, "lo_dex": "uniswap", "hi_dex": "aerodrome", "min_tvl": 654321.03, "whale": true, "samples": [[0.0, 0.8608, -0.252], [1.8, 0.8608, -0.252], [3.6, 0.8608, -0.252], [5.4, 0.8608, -0.252], [7.2, 0.8608, -0.252], [9.0, 0.8608, -0.252], [10.8, 0.8608, -0.252]]}, {"id": "28801d71", "chain": "base", "token": "WETH", "t0": "2026-06-27T20:56:19.579535+00:00", "entry_spread": 0.687, "lo_dex": "uniswap", "hi_dex": "uniswap", "min_tvl": 746075.17, "whale": true, "samples": [[0.0, 0.687, -0.3507], [1.8, 0.687, -0.3507], [3.6, 0.687, -0.3507], [5.4, 0.6755, -0.3622]]}, {"id": "2db29b9d", "chain": "solana", "token": "SOL", "t0": "2026-06-27T20:58:07.493399+00:00", "entry_spread": 0.4508, "lo_dex": "raydium", "hi_dex": "orca", "min_tvl": 561169.04, "whale": true, "samples": [[0.0, 0.4508, -0.7625], [1.8, 0.5216, -0.1428], [3.6, 2.0286, 0.8174]]}]