[{"id": "16e7eab4", "chain": "base", "token": "VIRTUAL", "t0": "2026-06-26T17:12:53.436659+00:00", "entry_spread": 1.055, "lo_dex": "aerodrome", "hi_dex": "aerodrome", "min_tvl": 421255.21, "whale": true, "samples": [[0.0, 1.055, -0.396], [12.6, 0.9043, -0.6199], [14.3, 0.8478, -0.6041], [15.9, 0.942, -0.5097], [17.5, 1.3941, -0.072], [19.2, 0.9565, -0.533], [20.8, 0.6939, -0.202], [22.5, 0.7689, -0.7211], [24.1, 0.6752, -0.2208]]}, {"id": "9df171e3", "chain": "base", "token": "AERO", "t0": "2026-06-26T17:12:53.436659+00:00", "entry_spread": 0.9506, "lo_dex": "aerodrome", "hi_dex": "aerodrome", "min_tvl": 2889054.41, "whale": true, "samples": [[0.0, 0.9506, 0.3107], [12.6, 1.0352, -0.6817], [14.3, 0.9934, -0.7236], [15.9, 0.889, -0.828], [17.5, 0.889, -0.828], [19.2, 0.889, -0.828], [20.8, 1.3079, 0.0819], [22.5, 1.0793, -0.6398], [24.1, 1.2264, -0.4927]]}, {"id": "20f3e819", "chain": "solana", "token": "MET", "t0": "2026-06-26T17:25:30.300424+00:00", "entry_spread": 0.8799, "lo_dex": "meteora", "hi_dex": "meteora", "min_tvl": 280474.85, "whale": true, "samples": [[0.0, 0.8799, -1.0467], [1.6, 0.6824, -0.3166], [3.3, 0.6203, -1.2909], [4.9, 0.7453, -1.1659], [6.6, 0.7453, -1.1659], [8.2, 0.9334, -0.9779], [9.9, 0.9334, -0.9779], [11.5, 1.375, -0.5363]]}, {"id": "56bcf624", "chain": "base", "token": "CBBTC", "t0": "2026-06-26T17:28:47.047399+00:00", "entry_spread": 1.0068, "lo_dex": "aerodrome", "hi_dex": "uniswap", "min_tvl": 389266.67, "whale": true, "samples": [[0.0, 1.0068, -0.5223], [1.6, 1.2108, 0.1199], [3.3, 0.9706, -0.5585], [4.9, 0.9706, -0.5585], [6.6, 2.9897, 1.2511], [8.2, 2.9897, 1.2511]]}, {"id": "ca3008a5", "chain": "solana", "token": "FARTCOIN ", "t0": "2026-06-26T17:32:04.337226+00:00", "entry_spread": 0.3831, "lo_dex": "raydium", "hi_dex": "orca", "min_tvl": 771216.86, "whale": true, "samples": [[0.0, 0.3831, -0.636], [1.6, 0.0769, -0.9452], [3.3, 0.0769, -0.9452], [4.9, 0.3864, -0.9261]]}, {"id": "3d0210b0", "chain": "base", "token": "EURC", "t0": "2026-06-26T17:35:21.521640+00:00", "entry_spread": 0.885, "lo_dex": "aerodrome", "hi_dex": "aerodrome", "min_tvl": 499269.32, "whale": true, "samples": [[0.0, 0.885, -0.4177], [1.6, 0.885, -0.418]]}, {"id": "77ed6b10", "chain": "base", "token": "WETH", "t0": "2026-06-26T17:35:21.521640+00:00", "entry_spread": 0.755, "lo_dex": "uniswap", "hi_dex": "0x03C01Acae3D0173a93d819efDc832C7C4F153B06", "min_tvl": 384941.09, "whale": true, "samples": [[0.0, 0.755, -0.7856], [1.6, 0.755, -0.7856]]}, {"id": "47ffe1cc", "chain": "solana", "token": "SOL", "t0": "2026-06-26T17:37:00.131764+00:00", "entry_spread": 0.7623, "lo_dex": "meteora", "hi_dex": "orca", "min_tvl": 655527.12, "whale": true, "samples": [[0.0, 0.7623, -0.3484]]}]