[{"id": "763f6e91", "chain": "base", "token": "VIRTUAL", "t0": "2026-06-26T23:31:39.382627+00:00", "entry_spread": 0.8536, "lo_dex": "aerodrome", "hi_dex": "aerodrome", "min_tvl": 415529.2, "whale": true, "samples": [[0.0, 0.8536, -0.6106], [1.6, 0.8918, -0.5724], [3.3, 0.8536, -0.6836], [4.9, 0.8344, -0.5991], [16.8, 0.8529, -0.2061], [18.6, 0.8529, -0.2061], [20.4, 0.8529, -0.2061], [22.2, 0.8529, -0.2061], [24.0, 0.8529, -0.2061], [25.8, 0.8529, -0.2061], [27.6, 0.8529, -0.2061], [29.4, 0.8529, -0.2061]]}, {"id": "d8ad466c", "chain": "base", "token": "VVV", "t0": "2026-06-26T23:33:17.954461+00:00", "entry_spread": 0.3693, "lo_dex": "uniswap", "hi_dex": "aerodrome", "min_tvl": 288972.53, "whale": true, "samples": [[0.0, 0.3693, -1.5164], [1.6, 0.3693, -1.5164], [3.3, 0.3693, -1.5164], [15.1, 0.6623, -1.2235], [16.9, 0.6623, -1.2235], [18.7, 0.6623, -1.2235], [20.5, 0.6623, -1.2235], [22.3, 0.6623, -1.2235], [24.1, 0.7358, -1.1499], [25.9, 0.8094, -1.0763], [27.7, 0.883, -1.0027]]}, {"id": "9e601224", "chain": "solana", "token": "SOL", "t0": "2026-06-26T23:48:25.700305+00:00", "entry_spread": 1.338, "lo_dex": "raydium", "hi_dex": "raydium", "min_tvl": 561097.44, "whale": true, "samples": [[0.0, 1.338, 0.1246], [1.8, 0.7405, -0.4674], [3.6, 0.6432, -0.0564], [5.4, 0.6573, -0.0424], [7.2, 0.5869, -0.1127], [9.0, 0.6432, -0.0564], [10.8, 0.5729, -0.5408], [12.6, 0.615, -0.0846]]}, {"id": "fe33fac2", "chain": "solana", "token": "ORE", "t0": "2026-06-26T23:50:13.271969+00:00", "entry_spread": 0.5372, "lo_dex": "meteora", "hi_dex": "orca", "min_tvl": 256525.54, "whale": true, "samples": [[0.0, 0.5372, -1.5226], [1.8, 0.5372, -1.5226], [3.6, 0.5372, -1.5226], [5.4, 0.6391, -1.4202], [7.2, 0.6391, -1.4202], [9.0, 0.6391, -1.4202], [10.8, 0.6391, -1.4202]]}, {"id": "1b3885de", "chain": "base", "token": "AERO", "t0": "2026-06-26T23:52:01.532904+00:00", "entry_spread": 1.1419, "lo_dex": "aerodrome", "hi_dex": "aerodrome", "min_tvl": 606725.39, "whale": true, "samples": [[0.0, 1.1419, -0.0189], [1.8, 1.0803, -0.1101], [3.6, 1.1874, -0.004], [5.4, 1.1874, -0.004], [7.2, 1.1446, -0.0451], [9.0, 1.0801, -0.0599]]}, {"id": "e9dacb6f", "chain": "solana", "token": "ARC", "t0": "2026-06-26T23:59:14.419208+00:00", "entry_spread": 3.7344, "lo_dex": "meteora", "hi_dex": "raydium", "min_tvl": 416132.77, "whale": false, "samples": [[0.0, 3.7344, 2.2727], [1.8, 3.7097, 2.2479]]}, {"id": "dd8a8944", "chain": "base", "token": "CBBTC", "t0": "2026-06-26T23:59:14.419208+00:00", "entry_spread": 1.3427, "lo_dex": "uniswap", "hi_dex": "aerodrome", "min_tvl": 385566.72, "whale": true, "samples": [[0.0, 1.3427, -0.1963], [1.8, 1.3473, -0.1916]]}]